gen_alt_text.py
gen_alt_text-0.3.dist-info/METADATA
gen_alt_text-0.3.dist-info/WHEEL
gen_alt_text-0.3.dist-info/entry_points.txt
gen_alt_text-0.3.dist-info/licenses/LICENSE
gen_alt_text-0.3.dist-info/RECORD
