Metadata-Version: 2.4
Name: gen-alt-text
Version: 0.3
Summary: Generate alt-text for images from a local or remote Ollama server running LLM vision models.
Project-URL: Homepage, https://codeberg.org/hyperreal/gen-alt-text
Project-URL: Issues, https://codeberg.org/hyperreal/gen-alt-text/issues
Author-email: Jeffrey Serio <hyperreal@fedoraproject.org>
License-File: LICENSE
Classifier: License :: OSI Approved :: GNU General Public License v3 or later (GPLv3+)
Classifier: Operating System :: OS Independent
Classifier: Programming Language :: Python :: 3
Requires-Python: >=3.10
Requires-Dist: docopt>=0.6.2
Requires-Dist: ollama>=0.4.4
Requires-Dist: rich>=13.9.4
